Metadata-Version: 1.0
Name: haoc-distributions
Version: 1.0
Summary: Gaussian distributions
Home-page: UNKNOWN
Author: Hao Cui
Author-email: chraggedbear@hotmail.com
License: UNKNOWN
Platform: UNKNOWN
